distributions/Binomialdistribution.py
distributions/Gaussiandistribution.py
distributions/Generaldistribution.py
distributions/__init__.py
hassn_distributions-0.1.dist-info/METADATA
hassn_distributions-0.1.dist-info/WHEEL
hassn_distributions-0.1.dist-info/top_level.txt
hassn_distributions-0.1.dist-info/RECORD
