Metadata-Version: 2.1
Name: hassn-distributions
Version: 0.1
Summary: Gaussian distributions
Home-page: UNKNOWN
Author: Hassn Hamada
Author-email: hassneltokhy4@gmail.com
License: UNKNOWN
Platform: UNKNOWN
